sat_tmp/__init__.py
sat_tmp/wokkel/__init__.py
sat_tmp/wokkel/data_form.py
sat_tmp/wokkel/mam.py
sat_tmp/wokkel/pubsub.py
sat_tmp/wokkel/rsm.py
sat_tmp/wokkel/test/__init__.py
sat_tmp/wokkel/test/test_pubsub.py
sat_tmp/wokkel/test/test_rsm.py
sat_tmp-0.8.0.data/data/share/doc/sat_tmp/COPYING
sat_tmp-0.8.0.data/data/share/doc/sat_tmp/README
sat_tmp-0.8.0.dist-info/COPYING
sat_tmp-0.8.0.dist-info/METADATA
sat_tmp-0.8.0.dist-info/WHEEL
sat_tmp-0.8.0.dist-info/top_level.txt
sat_tmp-0.8.0.dist-info/RECORD
